mcp_fetch_streamablehttp_server/__init__.py
mcp_fetch_streamablehttp_server/__main__.py
mcp_fetch_streamablehttp_server/fetch_handler.py
mcp_fetch_streamablehttp_server/server.py
mcp_fetch_streamablehttp_server/transport.py
mcp_fetch_streamablehttp_server-0.2.0.dist-info/METADATA
mcp_fetch_streamablehttp_server-0.2.0.dist-info/WHEEL
mcp_fetch_streamablehttp_server-0.2.0.dist-info/top_level.txt
mcp_fetch_streamablehttp_server-0.2.0.dist-info/RECORD
