Metadata-Version: 2.4
Name: mcp-fetch-streamablehttp-server
Version: 0.2.0
Summary: MCP fetch server with native Streamable HTTP transport implementation
Author-email: Andreas Trawoeger <atrawog@gmail.com>
License-Expression: Apache-2.0
Project-URL: Homepage, https://github.com/atrawog/mcp-oauth-gateway/tree/main/mcp-fetch-streamablehttp-server
Project-URL: Repository, https://github.com/atrawog/mcp-oauth-gateway/tree/main/mcp-fetch-streamablehttp-server
Project-URL: Issues, https://github.com/atrawog/mcp-oauth-gateway/issues
Project-URL: Documentation, https://atrawog.github.io/mcp-oauth-gateway
Requires-Python: >=3.11
Requires-Dist: mcp>=1.2.1
Requires-Dist: httpx>=0.28.1
Requires-Dist: pydantic>=2.10.4
Requires-Dist: pydantic-settings>=2.7.0
Requires-Dist: python-dotenv>=1.0.1
Requires-Dist: robotspy>=0.8.0
Requires-Dist: beautifulsoup4>=4.12.3
Requires-Dist: aiofiles>=24.0.0
Requires-Dist: uvloop>=0.21.0
Requires-Dist: uvicorn>=0.34.0
Requires-Dist: fastapi>=0.115.6
Provides-Extra: dev
Requires-Dist: pytest>=8.3.4; extra == "dev"
Requires-Dist: pytest-asyncio>=0.25.2; extra == "dev"
Requires-Dist: pytest-cov>=6.0.0; extra == "dev"
Requires-Dist: ruff>=0.9.1; extra == "dev"
